Cappuccino/CMSParser.py
Cappuccino/G1GCParser.py
Cappuccino/GCParser.py
Cappuccino/__init__.py
Cappuccino/auxiliary.py
cappuccino-0.1.5.dist-info/METADATA
cappuccino-0.1.5.dist-info/WHEEL
cappuccino-0.1.5.dist-info/top_level.txt
cappuccino-0.1.5.dist-info/RECORD
