Metadata-Version: 2.1
Name: cappuccino
Version: 0.1.5
Summary: Java GC Log Parser written in Python
Home-page: https://github.com/vidigalp/cappuccino
Author: vidigalp
Author-email: pedro.vidigal@instaclustr.com
License: UNKNOWN
Platform: UNKNOWN
Requires-Dist: numpy
Requires-Dist: pandas
Requires-Dist: python-dateutil
Requires-Dist: pytz
Requires-Dist: six
Requires-Dist: tqdm
